_mpkg123/__init__.py
_mpkg123/__main__.py
mpkg123-0.0.0.dist-info/METADATA
mpkg123-0.0.0.dist-info/WHEEL
mpkg123-0.0.0.dist-info/top_level.txt
mpkg123-0.0.0.dist-info/RECORD
