Metadata-Version: 2.1
Name: mpkg123
Version: 0.0.0
Summary: UNKNOWN
Home-page: UNKNOWN
License: UNKNOWN
Platform: UNKNOWN
Requires-Dist: pytelegrambotapi
Requires-Dist: chromepass
